{"0":{},
"1":{"playlist":{"n":"1.Playlist", "ps":[2,3,4,5,6,7,8,9,10,11,14,15],"dur":[200,200,200,200,200,200,200,200,200,200,200,200],"transition":[17,17,17,17,17,17,17,17,17,17,17,17],"repeat":0,"r":true,"end":0},"on":true},
"19":{"playlist":{"n":"2. Tentacle presets","ps":[15,16,17,18,20],"dur":[300,300,300,300,30],"transition":[50,50,50,50,50],"repeat":0,"r":false,"end":0},"on":true},
"2":{"n":"2.Purple Burps","on":true,"bri":128,"transition":7,"mainseg":0,"seg":[{"id":0,"start":0,"stop":300,"grp":1,"spc":0,"of":0,"on":true,"frz":false,"bri":255,"cct":127,"col":[[236,64,255],[0,0,0],[0,0,0]],"fx":87,"sx":115,"ix":255,"pal":65,"sel":true,"rev":false,"mi":false},{"stop":0},{"stop":0},{"stop":0},{"stop":0},{"stop":0},{"stop":0},{"stop":0},{"stop":0},{"stop":0},{"stop":0},{"stop":0},{"stop":0},{"stop":0},{"stop":0},{"stop":0}]},
"3":{"n":"3.Tron Prince","on":true,"bri":128,"transition":7,"mainseg":0,"seg":[{"id":0,"start":0,"stop":300,"grp":1,"spc":0,"of":0,"on":true,"frz":false,"bri":255,"cct":127,"col":[[236,64,255],[45,50,108],[0,0,0]],"fx":64,"sx":115,"ix":255,"pal":3,"sel":true,"rev":false,"mi":false},{"stop":0},{"stop":0},{"stop":0},{"stop":0},{"stop":0},{"stop":0},{"stop":0},{"stop":0},{"stop":0},{"stop":0},{"stop":0},{"stop":0},{"stop":0},{"stop":0},{"stop":0}]},
"4":{"n":"4.Burnt Wash","on":true,"bri":129,"transition":7,"mainseg":0,"seg":[{"id":0,"start":0,"stop":300,"grp":1,"spc":0,"of":0,"on":true,"frz":false,"bri":255,"cct":127,"col":[[236,64,255],[0,0,0],[0,0,0]],"fx":113,"sx":125,"ix":100,"pal":32,"sel":true,"rev":false,"mi":false},{"stop":0},{"stop":0},{"stop":0},{"stop":0},{"stop":0},{"stop":0},{"stop":0},{"stop":0},{"stop":0},{"stop":0},{"stop":0},{"stop":0},{"stop":0},{"stop":0},{"stop":0}]},
"5":{"n":"5.Lava Love","on":true,"bri":128,"transition":7,"mainseg":0,"seg":[{"id":0,"start":0,"stop":300,"grp":1,"spc":0,"of":0,"on":true,"frz":false,"bri":255,"cct":127,"col":[[255,0,255],[0,0,0],[0,0,0]],"fx":115,"sx":115,"ix":255,"pal":8,"sel":true,"rev":false,"mi":false},{"stop":0},{"stop":0},{"stop":0},{"stop":0},{"stop":0},{"stop":0},{"stop":0},{"stop":0},{"stop":0},{"stop":0},{"stop":0},{"stop":0},{"stop":0},{"stop":0},{"stop":0}]},
"6":{"n":"6.Purple On Green","on":true,"bri":128,"transition":7,"mainseg":0,"seg":[{"id":0,"start":0,"stop":300,"grp":1,"spc":0,"of":0,"on":true,"frz":false,"bri":255,"cct":127,"col":[[166,0,255],[79,111,0],[0,0,0]],"fx":64,"sx":24,"ix":255,"pal":3,"sel":true,"rev":false,"mi":false},{"stop":0},{"stop":0},{"stop":0},{"stop":0},{"stop":0},{"stop":0},{"stop":0},{"stop":0},{"stop":0},{"stop":0},{"stop":0},{"stop":0},{"stop":0},{"stop":0},{"stop":0}]},
"7":{"n":"7.Buzzing Fairies","on":true,"bri":129,"transition":7,"mainseg":0,"seg":[{"id":0,"start":0,"stop":300,"grp":1,"spc":0,"of":0,"on":true,"frz":false,"bri":255,"cct":127,"col":[[236,64,255],[0,0,0],[0,0,0]],"fx":70,"sx":125,"ix":100,"pal":59,"sel":true,"rev":false,"mi":false},{"stop":0},{"stop":0},{"stop":0},{"stop":0},{"stop":0},{"stop":0},{"stop":0},{"stop":0},{"stop":0},{"stop":0},{"stop":0},{"stop":0},{"stop":0},{"stop":0},{"stop":0}]},
"8":{"n":"8.Rainbow worms","on":true,"bri":128,"transition":7,"mainseg":0,"seg":[{"id":0,"start":0,"stop":300,"grp":1,"spc":0,"of":0,"on":true,"frz":false,"bri":255,"cct":127,"col":[[255,0,255],[0,0,0],[0,0,0]],"fx":111,"sx":32,"ix":29,"pal":1,"sel":true,"rev":false,"mi":false},{"stop":0},{"stop":0},{"stop":0},{"stop":0},{"stop":0},{"stop":0},{"stop":0},{"stop":0},{"stop":0},{"stop":0},{"stop":0},{"stop":0},{"stop":0},{"stop":0},{"stop":0}]},
"9":{"n":"9.Pick up a Bouncy friend ","on":true,"bri":129,"transition":7,"mainseg":0,"seg":[{"id":0,"start":0,"stop":300,"grp":1,"spc":0,"of":0,"on":true,"frz":false,"bri":255,"cct":127,"col":[[79,255,243],[54,255,36],[31,31,255]],"fx":91,"sx":125,"ix":100,"pal":59,"sel":true,"rev":false,"mi":false},{"stop":0},{"stop":0},{"stop":0},{"stop":0},{"stop":0},{"stop":0},{"stop":0},{"stop":0},{"stop":0},{"stop":0},{"stop":0},{"stop":0},{"stop":0},{"stop":0},{"stop":0}]},
"10":{"n":"10.Fairy fly","on":true,"bri":127,"transition":7,"mainseg":0,"seg":[{"id":0,"start":0,"stop":300,"grp":1,"spc":0,"of":0,"on":true,"frz":false,"bri":255,"cct":127,"col":[[236,64,255],[0,0,0],[0,0,0]],"fx":75,"sx":115,"ix":255,"pal":46,"sel":true,"rev":false,"mi":false},{"stop":0},{"stop":0},{"stop":0},{"stop":0},{"stop":0},{"stop":0},{"stop":0},{"stop":0},{"stop":0},{"stop":0},{"stop":0},{"stop":0},{"stop":0},{"stop":0},{"stop":0}]},
"11":{"n":"11.Mexican candy","on":true,"bri":128,"transition":7,"mainseg":0,"seg":[{"id":0,"start":0,"stop":300,"grp":1,"spc":0,"of":0,"on":true,"frz":false,"bri":255,"cct":127,"col":[[236,64,255],[45,50,108],[0,0,0]],"fx":72,"sx":115,"ix":255,"pal":24,"sel":true,"rev":false,"mi":false},{"stop":0},{"stop":0},{"stop":0},{"stop":0},{"stop":0},{"stop":0},{"stop":0},{"stop":0},{"stop":0},{"stop":0},{"stop":0},{"stop":0},{"stop":0},{"stop":0},{"stop":0}]},
"12":{"win":"T=0","n":"12. Off"},
"13":{"win":"T=1","n":"13. On"},
"14":{"n":"14.Random Phyre 2012","on":true,"bri":129,"transition":7,"mainseg":0,"seg":[{"id":0,"start":0,"stop":300,"grp":1,"spc":0,"of":0,"on":true,"frz":false,"bri":255,"cct":127,"col":[[236,64,255],[0,0,0],[0,0,0]],"fx":66,"sx":115,"ix":112,"pal":1,"sel":true,"rev":false,"mi":false},{"stop":0},{"stop":0},{"stop":0},{"stop":0},{"stop":0},{"stop":0},{"stop":0},{"stop":0},{"stop":0},{"stop":0},{"stop":0},{"stop":0},{"stop":0},{"stop":0},{"stop":0}]},
"15":{"n":"15. Tntcl - Anger mode ","on":true,"bri":128,"transition":7,"mainseg":0,"seg":[{"id":0,"start":0,"stop":50,"grp":1,"spc":0,"of":0,"on":true,"bri":255,"cct":127,"col":[[255,0,255],[0,0,0],[0,0,0]],"fx":115,"sx":115,"ix":255,"c1x":128,"c2x":128,"c3x":128,"pal":8,"sel":false,"rev":false,"rev2D":false,"mi":false,"rot2D":false},{"id":1,"start":50,"stop":100,"grp":1,"spc":0,"of":0,"on":true,"bri":255,"cct":127,"col":[[102,153,0],[0,0,0],[0,0,0]],"fx":176,"sx":128,"ix":128,"c1x":0,"c2x":0,"c3x":0,"pal":35,"sel":false,"rev":false,"rev2D":false,"mi":false,"rot2D":false},{"id":2,"start":100,"stop":150,"grp":1,"spc":0,"of":0,"on":true,"bri":255,"cct":127,"col":[[204,21,14],[0,0,0],[0,0,0]],"fx":78,"sx":128,"ix":128,"c1x":0,"c2x":0,"c3x":0,"pal":32,"sel":false,"rev":false,"rev2D":false,"mi":false,"rot2D":false},{"id":3,"start":150,"stop":200,"grp":1,"spc":0,"of":0,"on":true,"bri":255,"cct":127,"col":[[0,51,204],[0,0,0],[0,0,0]],"fx":115,"sx":128,"ix":169,"c1x":0,"c2x":0,"c3x":0,"pal":8,"sel":true,"rev":false,"rev2D":false,"mi":false,"rot2D":false},{"stop":0},{"stop":0},{"stop":0},{"stop":0},{"stop":0},{"stop":0},{"stop":0},{"stop":0},{"stop":0},{"stop":0},{"stop":0},{"stop":0},{"stop":0},{"stop":0},{"stop":0},{"stop":0},{"stop":0},{"stop":0},{"stop":0},{"stop":0},{"stop":0},{"stop":0},{"stop":0},{"stop":0},{"stop":0},{"stop":0},{"stop":0},{"stop":0}]},
"16":{"n":"16.Ocean Camo","on":true,"bri":128,"transition":7,"mainseg":0,"seg":[{"id":0,"start":0,"stop":50,"grp":1,"spc":0,"of":0,"on":true,"bri":255,"cct":127,"col":[[255,0,255],[0,0,0],[0,0,0]],"fx":128,"sx":115,"ix":255,"c1x":128,"c2x":128,"c3x":128,"pal":22,"sel":false,"rev":false,"rev2D":false,"mi":false,"rot2D":false},{"id":1,"start":50,"stop":100,"grp":1,"spc":0,"of":0,"on":true,"bri":255,"cct":127,"col":[[102,153,0],[0,0,0],[0,0,0]],"fx":129,"sx":128,"ix":128,"c1x":0,"c2x":0,"c3x":0,"pal":15,"sel":false,"rev":false,"rev2D":false,"mi":false,"rot2D":false},{"id":2,"start":100,"stop":150,"grp":1,"spc":0,"of":0,"on":true,"bri":255,"cct":127,"col":[[204,21,14],[0,0,0],[0,0,0]],"fx":133,"sx":128,"ix":128,"c1x":0,"c2x":0,"c3x":0,"pal":22,"sel":false,"rev":false,"rev2D":false,"mi":false,"rot2D":false},{"id":3,"start":150,"stop":200,"grp":1,"spc":0,"of":0,"on":true,"bri":255,"cct":127,"col":[[0,51,204],[0,0,0],[0,0,0]],"fx":148,"sx":128,"ix":169,"c1x":0,"c2x":0,"c3x":0,"pal":9,"sel":true,"rev":false,"rev2D":false,"mi":false,"rot2D":false},{"stop":0},{"stop":0},{"stop":0},{"stop":0},{"stop":0},{"stop":0},{"stop":0},{"stop":0},{"stop":0},{"stop":0},{"stop":0},{"stop":0},{"stop":0},{"stop":0},{"stop":0},{"stop":0},{"stop":0},{"stop":0},{"stop":0},{"stop":0},{"stop":0},{"stop":0},{"stop":0},{"stop":0},{"stop":0},{"stop":0},{"stop":0},{"stop":0}]},
"17":{"n":"17. T - Fade cool","on":true,"bri":128,"transition":7,"mainseg":0,"seg":[{"id":0,"start":0,"stop":50,"grp":1,"spc":0,"of":0,"on":true,"bri":255,"cct":127,"col":[[255,0,255],[60,0,255],[0,0,0]],"fx":12,"sx":115,"ix":255,"c1x":128,"c2x":128,"c3x":128,"pal":44,"sel":false,"rev":false,"rev2D":false,"mi":false,"rot2D":false},{"id":1,"start":50,"stop":100,"grp":1,"spc":0,"of":0,"on":true,"bri":255,"cct":127,"col":[[102,153,0],[62,59,255],[0,0,0]],"fx":12,"sx":128,"ix":128,"c1x":0,"c2x":0,"c3x":0,"pal":28,"sel":false,"rev":false,"rev2D":false,"mi":false,"rot2D":false},{"id":2,"start":100,"stop":150,"grp":1,"spc":0,"of":0,"on":true,"bri":255,"cct":127,"col":[[204,21,14],[134,41,255],[0,0,0]],"fx":12,"sx":128,"ix":128,"c1x":0,"c2x":0,"c3x":0,"pal":40,"sel":false,"rev":false,"rev2D":false,"mi":false,"rot2D":false},{"id":3,"start":150,"stop":200,"grp":1,"spc":0,"of":0,"on":true,"bri":255,"cct":127,"col":[[134,20,204],[41,52,255],[0,0,0]],"fx":12,"sx":128,"ix":169,"c1x":0,"c2x":0,"c3x":0,"pal":30,"sel":true,"rev":false,"rev2D":false,"mi":false,"rot2D":false},{"stop":0},{"stop":0},{"stop":0},{"stop":0},{"stop":0},{"stop":0},{"stop":0},{"stop":0},{"stop":0},{"stop":0},{"stop":0},{"stop":0},{"stop":0},{"stop":0},{"stop":0},{"stop":0},{"stop":0},{"stop":0},{"stop":0},{"stop":0},{"stop":0},{"stop":0},{"stop":0},{"stop":0},{"stop":0},{"stop":0},{"stop":0},{"stop":0}]},
"18":{"n":"18.T Fade cool fast","on":true,"bri":128,"transition":7,"mainseg":0,"seg":[{"id":0,"start":0,"stop":50,"grp":1,"spc":0,"of":0,"on":true,"bri":255,"cct":127,"col":[[255,0,255],[60,0,255],[0,0,0]],"fx":12,"sx":241,"ix":95,"c1x":128,"c2x":128,"c3x":128,"pal":44,"sel":false,"rev":false,"rev2D":false,"mi":false,"rot2D":false},{"id":1,"start":50,"stop":100,"grp":1,"spc":0,"of":0,"on":true,"bri":255,"cct":127,"col":[[102,153,0],[62,59,255],[0,0,0]],"fx":12,"sx":208,"ix":53,"c1x":0,"c2x":0,"c3x":0,"pal":28,"sel":false,"rev":false,"rev2D":false,"mi":false,"rot2D":false},{"id":2,"start":100,"stop":150,"grp":1,"spc":0,"of":0,"on":true,"bri":255,"cct":127,"col":[[204,21,14],[134,41,255],[0,0,0]],"fx":12,"sx":244,"ix":255,"c1x":0,"c2x":0,"c3x":0,"pal":40,"sel":false,"rev":false,"rev2D":false,"mi":false,"rot2D":false},{"id":3,"start":150,"stop":200,"grp":1,"spc":0,"of":0,"on":true,"bri":255,"cct":127,"col":[[134,20,204],[41,52,255],[0,0,0]],"fx":12,"sx":255,"ix":234,"c1x":0,"c2x":0,"c3x":0,"pal":58,"sel":true,"rev":false,"rev2D":false,"mi":false,"rot2D":false},{"stop":0},{"stop":0},{"stop":0},{"stop":0},{"stop":0},{"stop":0},{"stop":0},{"stop":0},{"stop":0},{"stop":0},{"stop":0},{"stop":0},{"stop":0},{"stop":0},{"stop":0},{"stop":0},{"stop":0},{"stop":0},{"stop":0},{"stop":0},{"stop":0},{"stop":0},{"stop":0},{"stop":0},{"stop":0},{"stop":0},{"stop":0},{"stop":0}]},
"20":{"n":"20.Mtrx-Binmap","on":true,"bri":128,"transition":7,"mainseg":0,"seg":[{"id":0,"start":0,"stop":200,"grp":1,"spc":0,"of":0,"on":true,"bri":255,"cct":127,"col":[[255,0,255],[0,0,0],[0,0,0]],"fx":142,"sx":32,"ix":29,"c1x":128,"c2x":128,"c3x":128,"pal":1,"sel":true,"rev":false,"rev2D":false,"mi":false,"rot2D":false},{"stop":0},{"stop":0},{"stop":0},{"stop":0},{"stop":0},{"stop":0},{"stop":0},{"stop":0},{"stop":0},{"stop":0},{"stop":0},{"stop":0},{"stop":0},{"stop":0},{"stop":0},{"stop":0},{"stop":0},{"stop":0},{"stop":0},{"stop":0},{"stop":0},{"stop":0},{"stop":0},{"stop":0},{"stop":0},{"stop":0},{"stop":0},{"stop":0},{"stop":0},{"stop":0},{"stop":0}]},
"21":{"n":"21.T Fade Rbow Limbs","on":true,"bri":128,"transition":7,"mainseg":0,"seg":[{"id":0,"start":0,"stop":50,"grp":1,"spc":0,"of":0,"on":true,"bri":255,"cct":127,"col":[[255,0,255],[255,0,0],[255,102,0]],"fx":12,"sx":115,"ix":255,"c1x":128,"c2x":128,"c3x":128,"pal":8,"sel":true,"rev":false,"rev2D":false,"mi":false,"rot2D":false},{"id":1,"start":50,"stop":100,"grp":1,"spc":0,"of":0,"on":true,"bri":255,"cct":127,"col":[[153,94,0],[255,196,0],[255,251,0]],"fx":12,"sx":128,"ix":128,"c1x":0,"c2x":0,"c3x":0,"pal":35,"sel":false,"rev":false,"rev2D":false,"mi":false,"rot2D":false},{"id":2,"start":100,"stop":150,"grp":1,"spc":0,"of":0,"on":true,"bri":255,"cct":127,"col":[[99,204,0],[4,255,0],[0,255,166]],"fx":12,"sx":128,"ix":128,"c1x":0,"c2x":0,"c3x":0,"pal":32,"sel":false,"rev":false,"rev2D":false,"mi":false,"rot2D":false},{"id":3,"start":150,"stop":200,"grp":1,"spc":0,"of":0,"on":true,"bri":255,"cct":127,"col":[[0,51,204],[51,0,255],[106,0,255]],"fx":12,"sx":128,"ix":169,"c1x":0,"c2x":0,"c3x":0,"pal":8,"sel":false,"rev":false,"rev2D":false,"mi":false,"rot2D":false},{"stop":0},{"stop":0},{"stop":0},{"stop":0},{"stop":0},{"stop":0},{"stop":0},{"stop":0},{"stop":0},{"stop":0},{"stop":0},{"stop":0},{"stop":0},{"stop":0},{"stop":0},{"stop":0},{"stop":0},{"stop":0},{"stop":0},{"stop":0},{"stop":0},{"stop":0},{"stop":0},{"stop":0},{"stop":0},{"stop":0},{"stop":0},{"stop":0}]},
"22":{"n":"T.22 Strobe out","on":true,"bri":127,"transition":7,"mainseg":0,"seg":[{"id":0,"start":0,"stop":50,"grp":1,"spc":0,"of":0,"on":true,"bri":255,"cct":127,"col":[[245,254,255],[0,0,0],[0,0,0]],"fx":25,"sx":255,"ix":161,"c1x":128,"c2x":128,"c3x":128,"pal":46,"sel":true,"rev":false,"rev2D":false,"mi":false,"rot2D":false},{"id":1,"start":50,"stop":100,"grp":1,"spc":0,"of":0,"on":true,"bri":255,"cct":127,"col":[[245,254,255],[0,0,0],[255,251,0]],"fx":25,"sx":139,"ix":233,"c1x":128,"c2x":128,"c3x":128,"pal":46,"sel":false,"rev":false,"rev2D":false,"mi":false,"rot2D":false},{"id":2,"start":100,"stop":150,"grp":1,"spc":0,"of":0,"on":true,"bri":255,"cct":127,"col":[[245,254,255],[0,0,0],[0,255,166]],"fx":25,"sx":220,"ix":77,"c1x":128,"c2x":128,"c3x":128,"pal":46,"sel":false,"rev":false,"rev2D":false,"mi":false,"rot2D":false},{"id":3,"start":150,"stop":200,"grp":1,"spc":0,"of":0,"on":true,"bri":255,"cct":127,"col":[[245,254,255],[0,0,0],[106,0,255]],"fx":25,"sx":139,"ix":233,"c1x":128,"c2x":128,"c3x":128,"pal":46,"sel":false,"rev":false,"rev2D":false,"mi":false,"rot2D":false},{"stop":0},{"stop":0},{"stop":0},{"stop":0},{"stop":0},{"stop":0},{"stop":0},{"stop":0},{"stop":0},{"stop":0},{"stop":0},{"stop":0},{"stop":0},{"stop":0},{"stop":0},{"stop":0},{"stop":0},{"stop":0},{"stop":0},{"stop":0},{"stop":0},{"stop":0},{"stop":0},{"stop":0},{"stop":0},{"stop":0},{"stop":0},{"stop":0}]}}